yitizi.cpython-38-darwin.so
yitizi/__init__.pyi
yitizi/yitizi.tsv
yitizi_cpy-1.1.0.dist-info/LICENSE
yitizi_cpy-1.1.0.dist-info/METADATA
yitizi_cpy-1.1.0.dist-info/WHEEL
yitizi_cpy-1.1.0.dist-info/top_level.txt
yitizi_cpy-1.1.0.dist-info/RECORD
