Metadata-Version: 2.1
Name: yitizi-cpy
Version: 1.1.0
Summary: Yitizi (異體字): Variant Sinographs
Author-email: Yuanhao 'Nyoeghau' Chen <nyoeghau@nyoeghau.com>
License: # MIT License
Project-URL: Homepage, https://github.com/edward-martyr/yitizi-cpy
Project-URL: Bug Tracker, https://github.com/edward-martyr/yitizi-cpy/issues
Classifier: Programming Language :: Python :: 3.10
Classifier: Programming Language :: Python :: 3.11
Classifier: License :: OSI Approved :: MIT License
Classifier: Development Status :: 1 - Planning
Classifier: Operating System :: OS Independent
Classifier: Natural Language :: Chinese (Simplified)
Classifier: Natural Language :: Chinese (Traditional)
Classifier: Topic :: Text Processing :: Linguistic
Requires-Python: >=3.7
License-File: LICENSE
